cascade/__init__.py
cascade/buffer.py
cascade/errors.py
cascade/interruption.py
cascade/processor.py
cascade/py.typed
cascade/types.py
cascade_vad-2.0.0.dist-info/licenses/LICENSE
cascade_vad-2.0.0.dist-info/METADATA
cascade_vad-2.0.0.dist-info/WHEEL
cascade_vad-2.0.0.dist-info/entry_points.txt
cascade_vad-2.0.0.dist-info/top_level.txt
cascade_vad-2.0.0.dist-info/RECORD
