Metadata-Version: 2.4
Name: cascade-vad
Version: 2.0.0
Summary: 高性能异步并行音频&VAD处理库
Author-email: Xucailiang <xucailiang.ai@gmail.com>
Maintainer-email: Xucailiang <xucailiang.ai@gmail.com>
License-Expression: MIT
Project-URL: Documentation, https://cascade-vad.readthedocs.io/
Project-URL: Repository, https://github.com/xucailiang/cascade
Project-URL: Issues, https://github.com/xucailiang/cascade/issues
Project-URL: Changelog, https://github.com/xucailiang/cascade/blob/main/CHANGELOG.md
Keywords: voice-activity-detection,vad,audio-processing,speech,async,parallel,high-performance
Classifier: Development Status :: 4 - Beta
Classifier: Intended Audience :: Developers
Classifier: Operating System :: OS Independent
Classifier: Programming Language :: Python :: 3
Classifier: Programming Language :: Python :: 3.11
Classifier: Programming Language :: Python :: 3.12
Classifier: Topic :: Multimedia :: Sound/Audio :: Analysis
Classifier: Topic :: Scientific/Engineering :: Artificial Intelligence
Classifier: Topic :: Software Development :: Libraries :: Python Modules
Classifier: Typing :: Typed
Requires-Python: >=3.10
License-File: LICENSE
Requires-Dist: pydantic<3.0.0,>=2.4.0
Requires-Dist: numpy<2.0.0,>=1.24.0
Requires-Dist: scipy<2.0.0,>=1.11.0
Requires-Dist: asyncio-throttle<2.0.0,>=1.0.0
Requires-Dist: torchaudio<3.0.0,>=2.7.1
Requires-Dist: silero-vad<6.0.0,>=5.1.2
Requires-Dist: soundfile<0.14.0,>=0.13.1
Requires-Dist: psutil<8.0.0,>=7.0.0
Provides-Extra: dev
Requires-Dist: black<26.0.0,>=25.1.0; extra == "dev"
Requires-Dist: isort<7.0.0,>=6.0.1; extra == "dev"
Requires-Dist: mypy<2.0.0,>=1.17.0; extra == "dev"
Requires-Dist: pre-commit<5.0.0,>=4.2.0; extra == "dev"
Requires-Dist: ruff<0.13.0,>=0.12.7; extra == "dev"
Requires-Dist: flake8<8.0.0,>=7.3.0; extra == "dev"
Provides-Extra: demo
Requires-Dist: fastapi<0.117.0,>=0.116.1; extra == "demo"
Requires-Dist: uvicorn<0.36.0,>=0.35.0; extra == "demo"
Requires-Dist: websockets<16.0.0,>=15.0.1; extra == "demo"
Requires-Dist: python-multipart<0.0.21,>=0.0.20; extra == "demo"
Requires-Dist: aiofiles<25.0.0,>=24.1.0; extra == "demo"
Requires-Dist: matplotlib<4.0.0,>=3.10.5; extra == "demo"
Provides-Extra: all
Requires-Dist: cascade[demo,dev]; extra == "all"
Dynamic: license-file
